gitgud/__init__.py
gitgud/gitgud.py
gitgud2-2.1.dist-info/LICENSE
gitgud2-2.1.dist-info/METADATA
gitgud2-2.1.dist-info/WHEEL
gitgud2-2.1.dist-info/entry_points.txt
gitgud2-2.1.dist-info/top_level.txt
gitgud2-2.1.dist-info/zip-safe
gitgud2-2.1.dist-info/RECORD
