Metadata-Version: 2.1
Name: gitgud2
Version: 2.1
Summary: Git Gud - a utility for when you are told to 'get good'
Home-page: https://github.com/kaeptmblaubaer1000/gitgud2
Author: Kaeptm Blaubaer
Author-email: kaeptmblaubaer1000@gmail.com
License: Public domain
Platform: UNKNOWN
Classifier: Development Status :: 5 - Production/Stable
Classifier: Environment :: Console
Classifier: Intended Audience :: Developers
Classifier: License :: Public Domain
Classifier: Operating System :: OS Independent
Classifier: Programming Language :: Python
Classifier: Programming Language :: Python :: 2
Classifier: Programming Language :: Python :: 3
Provides: gitgud
Requires-Dist: argparse
Requires-Dist: pyfiglet
